temporalio_server/__init__.py
temporalio_server/main.py
temporalio_server/py.typed
temporalio_server/bin/temporal
dandavison_temporalio_server-0.1.13.dist-info/METADATA
dandavison_temporalio_server-0.1.13.dist-info/WHEEL
dandavison_temporalio_server-0.1.13.dist-info/entry_points.txt
dandavison_temporalio_server-0.1.13.dist-info/licenses/LICENSE
dandavison_temporalio_server-0.1.13.dist-info/RECORD
