Metadata-Version: 2.4
Name: dandavison-temporalio-server
Version: 0.1.13
Summary: Python wrapper for the Temporal development server CLI
Author-email: Dan Davison <dan.davison@temporal.io>
License-File: LICENSE
Classifier: Development Status :: 4 - Beta
Classifier: Intended Audience :: Developers
Classifier: License :: OSI Approved :: MIT License
Classifier: Operating System :: OS Independent
Classifier: Programming Language :: Python :: 3
Classifier: Programming Language :: Python :: 3.9
Classifier: Programming Language :: Python :: 3.10
Classifier: Programming Language :: Python :: 3.11
Classifier: Programming Language :: Python :: 3.12
Classifier: Programming Language :: Python :: 3.13
Classifier: Topic :: Software Development :: Build Tools
Classifier: Topic :: System :: Distributed Computing
Requires-Python: >=3.9
Provides-Extra: examples
Requires-Dist: temporalio>=1.0.0; extra == 'examples'
